notarizer/__init__.py
notarizer/cli.py
notarizer/converter.py
notarizer/credentials_repository.py
notarizer/cryptography_wrapper.py
notarizer/docker_gateway.py
notarizer/exceptions.py
notarizer/image_signer.py
notarizer/image_verifier.py
notarizer/templates.py
notarizer/test/__init__.py
notarizer/test/mocked_data.py
notarizer/test/test_sign_images.py
notarizer/test/test_verify_signature.py
notarizer-1.0.1.dist-info/LICENSE
notarizer-1.0.1.dist-info/METADATA
notarizer-1.0.1.dist-info/WHEEL
notarizer-1.0.1.dist-info/entry_points.txt
notarizer-1.0.1.dist-info/top_level.txt
notarizer-1.0.1.dist-info/RECORD
