Metadata-Version: 2.1
Name: notarizer
Version: 1.0.1
Summary: Notarizer is a tool that provides a way of verifying the authenticity of docker images.
Home-page: https://github.com/Farfetch/notarizer.git
Author: Farfetch
Author-email: opensource@farfetch.com
License: MIT License (MIT)
Platform: UNKNOWN
Requires-Dist: appdirs (==1.4.4)
Requires-Dist: astroid (==2.4.2)
Requires-Dist: attrs (==19.3.0)
Requires-Dist: black (==19.10b0)
Requires-Dist: certifi (==2020.6.20)
Requires-Dist: cffi (==1.14.0)
Requires-Dist: chardet (==3.0.4)
Requires-Dist: click (==7.1.2)
Requires-Dist: colorama (==0.4.3)
Requires-Dist: cryptography (==2.9.2)
Requires-Dist: docker (==4.2.2)
Requires-Dist: idna (==2.10)
Requires-Dist: isort (==4.3.21)
Requires-Dist: lazy-object-proxy (==1.4.3)
Requires-Dist: mccabe (==0.6.1)
Requires-Dist: pathspec (==0.8.0)
Requires-Dist: pycodestyle (==2.6.0)
Requires-Dist: pycparser (==2.20)
Requires-Dist: pylint (==2.5.3)
Requires-Dist: regex (==2020.6.8)
Requires-Dist: requests (==2.24.0)
Requires-Dist: six (==1.15.0)
Requires-Dist: toml (==0.10.1)
Requires-Dist: typed-ast (==1.4.1)
Requires-Dist: urllib3 (==1.25.9)
Requires-Dist: websocket-client (==0.57.0)
Requires-Dist: wrapt (==1.12.1)
